lalib/__init__.py
lalib-0.4.2.dist-info/LICENSE.txt
lalib-0.4.2.dist-info/METADATA
lalib-0.4.2.dist-info/WHEEL
lalib-0.4.2.dist-info/RECORD
