Metadata-Version: 2.1
Name: lalib
Version: 0.4.2
Summary: A Python library to study linear algebra
Home-page: https://github.com/webartifex/lalib
License: MIT
Author: Alexander Hess
Author-email: alexander@webartifex.biz
Requires-Python: >=3.9,<4.0
Classifier: Development Status :: 4 - Beta
Classifier: Intended Audience :: Developers
Classifier: Intended Audience :: Education
Classifier: Intended Audience :: Science/Research
Classifier: License :: OSI Approved :: MIT License
Classifier: Programming Language :: Python :: 3
Classifier: Programming Language :: Python :: 3.9
Classifier: Programming Language :: Python :: 3.10
Classifier: Programming Language :: Python :: 3.11
Classifier: Programming Language :: Python :: 3.12
Project-URL: Documentation, https://lalib.readthedocs.io
Project-URL: Issues Tracker, https://github.com/webartifex/lalib/issues
Project-URL: Repository, https://github.com/webartifex/lalib
